__init__.py
tomfoolery/.gitignore
tomfoolery/__init__.py
tomfoolery/main.py
tomfoolery/dialogs/__init__.py
tomfoolery/dialogs/dialog_config.py
tomfoolery/dialogs/dialog_dirs.py
tomfoolery/resources/512.png
tomfoolery/resources/64.png
tomfoolery/resources/64_smooth.png
tomfoolery/resources/missing_image.png
tomfoolery/resources/stylesheet.qss
tomfoolery/scrapers/__init__.py
tomfoolery/scrapers/scrape_bandcamp.py
tomfoolery/scrapers/scrape_soundcloud.py
tomfoolery/scrapers/scrape_youtube.py
tomfoolery/ui/__init__.py
tomfoolery/ui/autocomplete.py
tomfoolery/ui/base.py
tomfoolery/ui/console.py
tomfoolery/ui/dialog_config.py
tomfoolery/ui/dialog_dir.py
tomfoolery/ui/main_window.py
tomfoolery/ui/tracklist.py
tomfoolery/ui/config/__init__.py
tomfoolery/ui/config/config_classes.py
tomfoolery/ui/designer_uis/dir_dialog.ui
tomfoolery/ui/designer_uis/main_window.py
tomfoolery/ui/designer_uis/main_window.ui
tomfoolery/utils/__init__.py
tomfoolery/utils/ffmpeg_progress.py
tomfoolery/utils/filename_handler.py
tomfoolery/utils/image_downloader.py
tomfoolery/utils/metadata.py
tomfoolery/utils/multithreading.py
tomfoolery/utils/scrape_common.py
tomfoolery/utils/unavailable_tracks.py
py_tomfoolery-0.0.9.dist-info/LICENSE
py_tomfoolery-0.0.9.dist-info/METADATA
py_tomfoolery-0.0.9.dist-info/WHEEL
py_tomfoolery-0.0.9.dist-info/entry_points.txt
py_tomfoolery-0.0.9.dist-info/top_level.txt
py_tomfoolery-0.0.9.dist-info/RECORD
