Metadata-Version: 2.1
Name: py-tomfoolery
Version: 0.0.9
Summary: SoundCloud / YouTube / Bandcamp downloader /w a GUI
Author: Tom Krut
Project-URL: Repository, https://github.com/tomkrut/tomfoolery.git
Keywords: soundcloud,youtube,bandcamp,scraper,downloader
Classifier: Programming Language :: Python :: 3
Requires-Python: >=3.9
License-File: LICENSE
Requires-Dist: PyQt6 >=6.5.2
Requires-Dist: appdirs >=1.4.4
Requires-Dist: clint >=0.5.1
Requires-Dist: debugpy >=1.6.7
Requires-Dist: demjson3 >=3.0.6
Requires-Dist: ffmpeg-python >=0.2.0
Requires-Dist: moviepy >=1.0.3
Requires-Dist: mutagen >=1.46.0
Requires-Dist: pathvalidate >=3.0.0
Requires-Dist: pytube >=15.0.0
Requires-Dist: Requests >=2.31.0
Requires-Dist: soundcloud-v2 >=1.6.0
Requires-Dist: tqdm >=4.65.0
